./entrypoints.py
entrypoints-0.1.dist-info/METADATA
entrypoints-0.1.dist-info/WHEEL
entrypoints-0.1.dist-info/RECORD
